vscode_django_notebook/__init__.py
vscode_django_notebook/main.py
vscode_django_notebook-0.1.0.dist-info/LICENSE
vscode_django_notebook-0.1.0.dist-info/METADATA
vscode_django_notebook-0.1.0.dist-info/WHEEL
vscode_django_notebook-0.1.0.dist-info/top_level.txt
vscode_django_notebook-0.1.0.dist-info/RECORD
