Metadata-Version: 2.1
Name: vscode-django-notebook
Version: 0.1.0
Summary: A utility to easily use Django in VS Code Jupyter Notebooks.
Home-page: https://github.com/WazedKhan/vscode-django-notebook
Author: Abdul Wajed Khan
Author-email: wajed.abdul.khan@gmail.com
Keywords: django jupyter vscode development
Classifier: Programming Language :: Python :: 3
Classifier: License :: OSI Approved :: MIT License
Classifier: Operating System :: OS Independent
Classifier: Framework :: Django
Classifier: Intended Audience :: Developers
Requires-Python: >=3.6
License-File: LICENSE
